mhcnuggets/README.md
mhcnuggets/__init__.py
mhcnuggets/user_guide.ipynb
mhcnuggets/data/__init__.py
mhcnuggets/data/production/__init__.py
mhcnuggets/data/production/examples_per_allele.pkl
mhcnuggets/data/production/mhcI/__init__.py
mhcnuggets/data/production/mhcI/alleles_with_trained_models.txt
mhcnuggets/data/production/mhcI/curated_training_data.csv
mhcnuggets/data/production/mhcI/hp_ic50s_cI.pkl
mhcnuggets/data/production/mhcI/hp_ic50s_first_percentiles_cI.pkl
mhcnuggets/data/production/mhcI/hp_ic50s_hp_lengths_cI.pkl
mhcnuggets/data/production/mhcI/hp_ic50s_positions_cI.pkl
mhcnuggets/data/production/mhcI/mhc_tuning.csv
mhcnuggets/data/production/mhcII/__init__.py
mhcnuggets/data/production/mhcII/alleles_with_trained_models.txt
mhcnuggets/data/production/mhcII/curated_training_data.csv
mhcnuggets/data/production/mhcII/hp_ic50s_cII.pkl
mhcnuggets/data/production/mhcII/hp_ic50s_first_percentiles_cII.pkl
mhcnuggets/data/production/mhcII/hp_ic50s_hp_lengths_cII.pkl
mhcnuggets/data/production/mhcII/hp_ic50s_positions_cII.pkl
mhcnuggets/data/production/mhcII/mhc_tuning.csv
mhcnuggets/data/test/__init__.py
mhcnuggets/data/test/test_peptides.peps
mhcnuggets/saves/__init__.py
mhcnuggets/saves/production/BoLA-212:01_BA.h5
mhcnuggets/saves/production/BoLA-613:01_BA.h5
mhcnuggets/saves/production/BoLA-A11:01_BA.h5
mhcnuggets/saves/production/BoLA-DRB302:01_BA.h5
mhcnuggets/saves/production/BoLA-DRB311:01_BA.h5
mhcnuggets/saves/production/BoLA-DRB312:01_BA.h5
mhcnuggets/saves/production/Eqca-101:01_BA.h5
mhcnuggets/saves/production/H-2-Db_BA.h5
mhcnuggets/saves/production/H-2-Dd_BA.h5
mhcnuggets/saves/production/H-2-IAb_BA.h5
mhcnuggets/saves/production/H-2-IAd_BA.h5
mhcnuggets/saves/production/H-2-IAk_BA.h5
mhcnuggets/saves/production/H-2-IAp_BA.h5
mhcnuggets/saves/production/H-2-IAq_BA.h5
mhcnuggets/saves/production/H-2-IAr_BA.h5
mhcnuggets/saves/production/H-2-IAs_BA.h5
mhcnuggets/saves/production/H-2-IAu_BA.h5
mhcnuggets/saves/production/H-2-IEb_BA.h5
mhcnuggets-2.4.1.dist-info/LICENSE
mhcnuggets-2.4.1.dist-info/METADATA
mhcnuggets-2.4.1.dist-info/WHEEL
mhcnuggets-2.4.1.dist-info/top_level.txt
mhcnuggets-2.4.1.dist-info/zip-safe
mhcnuggets-2.4.1.dist-info/RECORD
