Metadata-Version: 2.1
Name: mhcnuggets
Version: 2.4.1
Summary: MHCnuggets: Neoantigen peptide MHC binding prediction for class I and II
Home-page: http://karchinlab.org/apps/mhcnuggets.html
Author: Melody Shao
Author-email: melody.xiaoshan.shao@gmail.com
License: Apache License
Classifier: Development Status :: 5 - Production/Stable
Classifier: Intended Audience :: Science/Research
Classifier: Topic :: Scientific/Engineering :: Bio-Informatics
License-File: LICENSE
Requires-Dist: numpy
Requires-Dist: scipy
Requires-Dist: scikit-learn
Requires-Dist: pandas
Requires-Dist: keras
Requires-Dist: tensorflow
Requires-Dist: varcode
